{"cameraMode":{"drawMode":0,"name":"Shaded","section":"Shading Mode"},"sceneLighting":true,"audioPlay":false,"sceneViewState":{"showFog":true,"showMaterialUpdate":false,"showSkybox":true,"showFlares":true,"showImageEffects":true,"showParticleSystems":true},"in2DMode":false,"pivot":{"x":-36.25411605834961,"y":-37.729103088378909,"z":164.99462890625},"rotation":{"x":-0.10263287276029587,"y":0.13741645216941834,"z":-0.014316263608634472,"w":-0.9850778579711914},"size":201.00732421875,"orthographic":false}